echogem/GRAPH_GUIDE.md
echogem/INSTALL.md
echogem/README.md
echogem/__init__.py
echogem/chunker.py
echogem/cli.py
echogem/graphe.py
echogem/models.py
echogem/processor.py
echogem/prompt_answer_store.py
echogem/requirements.txt
echogem/setup.py
echogem/usage_cache.py
echogem/vector_store.py
echogem/.github/workflows/ci.yml
echogem/demos/01_basic_workflow_demo.py
echogem/demos/02_cli_demo.py
echogem/demos/02_cli_mastery_demo.py
echogem/demos/03_api_demo.py
echogem/demos/03_api_integration_demo.py
echogem/demos/04_academic_paper_demo.py
echogem/demos/05_meeting_transcript_demo.py
echogem/demos/08_advanced_chunk_management_demo.py
echogem/demos/09_performance_benchmarking_demo.py
echogem/demos/12_graph_visualization_demo.py
echogem/demos/13_batch_processing_demo.py
echogem/demos/14_usage_analytics_demo.py
echogem/demos/README.md
echogem/examples/advanced_usage.py
echogem/examples/basic_usage.py
echogem/examples/cli_usage_example.py
echogem/examples/graph_visualization.py
echogem/examples/graph_visualization_demo.py
echogem/examples/sample_transcript.txt
echogem/legacy/01_initial_chunking_approach.py
echogem/legacy/02_basic_vector_store.py
echogem/legacy/03_old_embedding_models.py
echogem/legacy/04_experimental_retrieval.py
echogem/legacy/05_old_usage_tracking.py
echogem/legacy/06_experimental_cli.py
echogem/legacy/07_old_package_structure.py
echogem/legacy/08_old_visualization_attempts.py
echogem/legacy/09_old_llm_integration.py
echogem/legacy/10_old_data_models.py
echogem/legacy/11_old_testing_approaches.py
echogem/legacy/12_old_error_handling.py
echogem/legacy/13_old_configuration.py
echogem/legacy/14_old_packaging.py
echogem/legacy/15_development_notes.py
echogem/legacy/ChunkResponseClass.ipynb
echogem/legacy/Chunker.ipynb
echogem/legacy/Chunking.py
echogem/legacy/Experiment with Embedding Models.py
echogem/legacy/GUI Attempt.py
echogem/legacy/Package Structure.py
echogem/legacy/Processor.ipynb
echogem/legacy/README.md
echogem-1.0.0.dist-info/licenses/LICENSE
echogem-1.0.0.dist-info/METADATA
echogem-1.0.0.dist-info/WHEEL
echogem-1.0.0.dist-info/entry_points.txt
echogem-1.0.0.dist-info/top_level.txt
echogem-1.0.0.dist-info/RECORD
