Metadata-Version: 2.4
Name: echogem
Version: 1.0.0
Summary: Intelligent Transcript Processing and Question Answering Library
Home-page: https://github.com/yourusername/echogem
Author: Your Name
Author-email: Your Name <your.email@example.com>
Maintainer-email: Your Name <your.email@example.com>
License: MIT
Project-URL: Homepage, https://github.com/yourusername/echogem
Project-URL: Documentation, https://github.com/yourusername/echogem#readme
Project-URL: Repository, https://github.com/yourusername/echogem
Project-URL: Bug Tracker, https://github.com/yourusername/echogem/issues
Project-URL: Source Code, https://github.com/yourusername/echogem
Keywords: transcript,chunking,vector-database,question-answering,ai,nlp,retrieval,pinecone,gemini,langchain
Classifier: Development Status :: 3 - Alpha
Classifier: Intended Audience :: Developers
Classifier: Intended Audience :: Science/Research
Classifier: License :: OSI Approved :: MIT License
Classifier: Operating System :: OS Independent
Classifier: Programming Language :: Python :: 3
Classifier: Programming Language :: Python :: 3.8
Classifier: Programming Language :: Python :: 3.9
Classifier: Programming Language :: Python :: 3.10
Classifier: Programming Language :: Python :: 3.11
Classifier: Programming Language :: Python :: 3.12
Classifier: Topic :: Scientific/Engineering :: Artificial Intelligence
Classifier: Topic :: Text Processing :: Linguistic
Classifier: Topic :: Software Development :: Libraries :: Python Modules
Requires-Python: >=3.8
License-File: LICENSE
Requires-Dist: google-generativeai>=0.3.0
Requires-Dist: pinecone-client>=2.2.0
Requires-Dist: sentence-transformers>=2.2.0
Requires-Dist: pygame>=2.0.0
Requires-Dist: numpy>=1.21.0
Requires-Dist: pydantic>=2.0.0
Requires-Dist: langchain>=0.1.0
Requires-Dist: langchain-google-genai>=0.0.5
Requires-Dist: langchain-core>=0.1.0
Requires-Dist: langchain-community>=0.0.10
Provides-Extra: dev
Requires-Dist: pytest>=6.0; extra == "dev"
Requires-Dist: pytest-cov>=2.0; extra == "dev"
Requires-Dist: black>=21.0; extra == "dev"
Requires-Dist: flake8>=3.8; extra == "dev"
Requires-Dist: mypy>=0.800; extra == "dev"
Provides-Extra: docs
Requires-Dist: sphinx>=4.0; extra == "docs"
Requires-Dist: sphinx-rtd-theme>=1.0; extra == "docs"
Dynamic: author
Dynamic: home-page
Dynamic: license-file
Dynamic: requires-python
